LICENSE
MANIFEST.in
README.rst
setup.py
anarchy_sphinx.egg-info/PKG-INFO
anarchy_sphinx.egg-info/SOURCES.txt
anarchy_sphinx.egg-info/dependency_links.txt
anarchy_sphinx.egg-info/entry_points.txt
anarchy_sphinx.egg-info/not-zip-safe
anarchy_sphinx.egg-info/top_level.txt
anarchy_theme/__init__.py
anarchy_theme/domainindex.html
anarchy_theme/globaltoc.html
anarchy_theme/layout.html
anarchy_theme/theme.conf
anarchy_theme/static/basic.css
swift_domain/__init__.py
swift_domain/autodoc.py
swift_domain/bootstrap.py
swift_domain/indexer.py
swift_domain/swift.py