Metadata-Version: 1.1
Name: anarchy-sphinx
Version: 0.3.1
Summary: AnarchyTools Theme and Swift support for Sphinx.
Home-page: https://github.com/AnarchyTools/anarchySphinx
Author: Johannes Schriewer
Author-email: hallo@dunkelstern.de
License: BSD
Platform: UNKNOWN
Classifier: Development Status :: 4 - Beta
Classifier: License :: OSI Approved :: BSD License
Classifier: Environment :: Console
Classifier: Environment :: Web Environment
Classifier: Intended Audience :: Developers
Classifier: Programming Language :: Python :: 3
Classifier: Operating System :: OS Independent
Classifier: Topic :: Documentation
Classifier: Topic :: Software Development :: Documentation
